Sequential/ADD/ADDx1.v
module ADDx1(A, B, C, S, carry);
    input A,B,C;
    output S, carry;
    wire w1, w2, w3;

    xor(w1, A, B);
    xor(S, w1, C);
    and(w2, A, B);
    and(w3, w1, C);
    or(carry, w3, w2);
endmodule

Sequential/ADD/ADDx1_test.v
`timescale 10ps/1ps
`include "ADDx1.v"
module ADDx1_test();

reg A, B, C;
wire signed sum;
wire carry;
integer i;

ADDx1 AT21(A, B, C, sum, carry);

initial
    begin
        $dumpfile("ADDx1_test.vcd");
        $dumpvars(0, ADDx1_test);
        {A, B, C} = 0;

        $monitor($time, ": A=%b, B=%b, C=%b, sum=%b, carry=%b\n", A, B, C, sum, carry);
            for(i = 0; i < 8; i = i + 1) 
            begin
                #1 {A,B,C} = i;
            end
    end
endmodule

Sequential/ADD/ADDx1_test.vcd
$date
	Tue Jan 24 21:00:08 2023
$end
$version
	Icarus Verilog
$end
$timescale
	1ps
$end
$scope module ADDx1_test $end
$var wire 1 ! sum $end
$var wire 1 " carry $end
$var reg 1 # A $end
$var reg 1 $ B $end
$var reg 1 % C $end
$var integer 32 & i [31:0] $end
$scope module AT21 $end
$var wire 1 # A $end
$var wire 1 $ B $end
$var wire 1 % C $end
$var wire 1 ! S $end
$var wire 1 " carry $end
$var wire 1 ' w1 $end
$var wire 1 ( w2 $end
$var wire 1 ) w3 $end
$upscope $end
$upscope $end
$enddefinitions $end
#0
$dumpvars
0)
0(
0'
b0 &
0%
0$
0#
0"
0!
$end
#10
b1 &
#20
1!
b10 &
1%
#30
1'
1!
b11 &
1$
0%
#40
1"
0!
1)
b100 &
1%
#50
0"
1!
0)
b101 &
1#
0$
0%
#60
1"
0!
1)
b110 &
1%
#70
0'
1(
0!
0)
b111 &
1$
0%
#80
1!
b1000 &
1%
