Sequential/SUB/SUBx1.v
module SUBx1(A, B, borrow_in, borrow_out, diff);

input A, B, borrow_in;
output diff, borrow_out;

// calculating difference
xor X1(w1, A, B);
xor X2(diff, w1, borrow_in);

// calculating borrow_out
xnor XN1(w2, A, B);
and A1(w3, borrow_in, w2);

not NT1(w4, A);
and A2(w5, w4, B);
or O1(borrow_out, w3, w5);

endmodule

Sequential/SUB/tb_SUBx1.v
`timescale 10ps/1ps
`include "SUBx1.v"
module tb_SUBx1();

reg A, B, borrow_in;
wire diff, borrow_out;
integer x;

SUBx1 SUB1(A, B, borrow_in, borrow_out, diff);

initial begin
    $dumpfile("tb_SUBx1.vcd");
    $dumpvars(0, tb_SUBx1);

    {A, B, borrow_in} = 0;

    for(x=0;x<=7;x=x+1)
    begin
        #10 {A, B, borrow_in}=x;
    end
end

always@(diff, borrow_out)
begin
        $display("time = %0t\t\t %b %b %b\t\t%b %b",$time, A, B, borrow_in, borrow_out, diff);
end

endmodule

// Commands to run (terminal)
// iverilog -o tb_SUBx1 tb_SUBx1.v SUBx1.v
// vvp tb_SUBx1
// gtkwave tb_SUBx1.vcd

Sequential/SUB/tb_SUBx1.vcd
$date
	Tue Jan 24 21:03:08 2023
$end
$version
	Icarus Verilog
$end
$timescale
	1ps
$end
$scope module tb_SUBx1 $end
$var wire 1 ! diff $end
$var wire 1 " borrow_out $end
$var reg 1 # A $end
$var reg 1 $ B $end
$var reg 1 % borrow_in $end
$var integer 32 & x [31:0] $end
$scope module SUB1 $end
$var wire 1 # A $end
$var wire 1 $ B $end
$var wire 1 % borrow_in $end
$var wire 1 " borrow_out $end
$var wire 1 ! diff $end
$var wire 1 ' w1 $end
$var wire 1 ( w2 $end
$var wire 1 ) w3 $end
$var wire 1 * w4 $end
$var wire 1 + w5 $end
$upscope $end
$upscope $end
$enddefinitions $end
#0
$dumpvars
0+
1*
0)
1(
0'
b0 &
0%
0$
0#
0"
0!
$end
#100
b1 &
#200
1"
1!
1)
b10 &
1%
#300
1'
0(
1+
1!
0)
b11 &
1$
0%
#400
0!
b100 &
1%
#500
0"
0*
0+
1!
b101 &
1#
0$
0%
#600
0!
b110 &
1%
#700
0'
1(
0!
b111 &
1$
0%
#800
1"
1!
1)
b1000 &
1%
